pymathics/hello/__init__.py
pymathics/hello/__main__.py
pymathics/hello/version.py
pymathics_hello-7.0.0.dist-info/COPYING.txt
pymathics_hello-7.0.0.dist-info/METADATA
pymathics_hello-7.0.0.dist-info/WHEEL
pymathics_hello-7.0.0.dist-info/top_level.txt
pymathics_hello-7.0.0.dist-info/RECORD
